aliceplex/schema/__init__.py
aliceplex/schema/format.py
aliceplex/schema/model.py
aliceplex/schema/verify.py
aliceplex/schema/schema/__init__.py
aliceplex/schema/schema/actor.py
aliceplex/schema/schema/album.py
aliceplex/schema/schema/artist.py
aliceplex/schema/schema/base.py
aliceplex/schema/schema/episode.py
aliceplex/schema/schema/movie.py
aliceplex/schema/schema/person.py
aliceplex/schema/schema/show.py
aliceplex_schema-3.1.2.dist-info/LICENSE
aliceplex_schema-3.1.2.dist-info/METADATA
aliceplex_schema-3.1.2.dist-info/WHEEL
aliceplex_schema-3.1.2.dist-info/top_level.txt
aliceplex_schema-3.1.2.dist-info/RECORD
